[
    {
        "title": "Data Analyst (REMOTE BILINGUAL)",
        "company": "Collabera",
        "location": "St Louis, MO",
        "date_posted": "Recent",
        "url": "https://www.linkedin.com/jobs/view/data-analyst-remote-bilingual-at-collabera-4232625340?position=6&pageNum=0&refId=zwTFcaToBICf7kteELeLOA%3D%3D&trackingId=HOKXPrPCfWi4Vzqv8Yesgg%3D%3D",
        "source": "LinkedIn",
        "scraped_date": "2025-05-22 04:01:48",
        "email_sent": true
    },
    {
        "title": "Ecosystem Development Engineer",
        "company": "CelerData",
        "location": "Menlo Park, CA",
        "date_posted": "Recent",
        "url": "https://www.linkedin.com/jobs/view/ecosystem-development-engineer-at-celerdata-4234803710?position=4&pageNum=0&refId=yrFkyMBse4CB1tCI8oYTGA%3D%3D&trackingId=m%2BVbcwCHVF7X3NGBAff0Mw%3D%3D",
        "source": "LinkedIn",
        "scraped_date": "2025-05-22 04:36:01",
        "email_sent": true
    },
    {
        "title": "Data Quality Engineer, Spanish",
        "company": "Cypress HCM",
        "location": "United States",
        "date_posted": "Recent",
        "url": "https://www.linkedin.com/jobs/view/data-quality-engineer-spanish-at-cypress-hcm-4232623562?position=6&pageNum=0&refId=yrFkyMBse4CB1tCI8oYTGA%3D%3D&trackingId=IKN396cLvDpn0U%2BTDbSV6A%3D%3D",
        "source": "LinkedIn",
        "scraped_date": "2025-05-22 04:36:01",
        "email_sent": false
    }
]