[
    {
        "title": "Software Engineer (Junior & New Grad)",
        "company": "Jobright.ai",
        "location": "California, United States",
        "date_posted": "Recent",
        "url": "https://www.linkedin.com/jobs/view/software-engineer-junior-new-grad-at-jobright-ai-4242616925?position=3&pageNum=0&refId=u8ZB%2BbKAIaPKv3ULIz2CVA%3D%3D&trackingId=C3HrPtFLuxPfJOdrxP8YpQ%3D%3D",
        "source": "LinkedIn",
        "scraped_date": "2025-06-05 08:48:32",
        "email_sent": false
    },
    {
        "title": "**** *******",
        "company": "*********",
        "location": "**********, ****** ******",
        "date_posted": "Recent",
        "url": "https://www.linkedin.com/jobs/view/data-analyst-at-tietalent-4245216023?position=4&pageNum=0&refId=u8ZB%2BbKAIaPKv3ULIz2CVA%3D%3D&trackingId=%2F7DnaN28F%2FuqpPfAWnB9xg%3D%3D",
        "source": "LinkedIn",
        "scraped_date": "2025-06-05 08:48:32",
        "email_sent": false
    },
    {
        "title": "******** ********, ** ***** (****** ******)",
        "company": "********.**",
        "location": "**********, ****** ******",
        "date_posted": "Recent",
        "url": "https://www.linkedin.com/jobs/view/software-engineer-ml-infra-active-hiring-at-jobright-ai-4238025319?position=5&pageNum=0&refId=u8ZB%2BbKAIaPKv3ULIz2CVA%3D%3D&trackingId=UP87tATVhPGUopLTL3DS0g%3D%3D",
        "source": "LinkedIn",
        "scraped_date": "2025-06-05 08:48:32",
        "email_sent": false
    },
    {
        "title": "******** ********, ********",
        "company": "******",
        "location": "****** ******",
        "date_posted": "Recent",
        "url": "https://www.linkedin.com/jobs/view/software-engineer-security-at-motive-4241857423?position=6&pageNum=0&refId=u8ZB%2BbKAIaPKv3ULIz2CVA%3D%3D&trackingId=JYGE93m1reIMCXQ%2BJirSIg%3D%3D",
        "source": "LinkedIn",
        "scraped_date": "2025-06-05 08:48:32",
        "email_sent": false
    },
    {
        "title": "******** ******** ** (****** ******)",
        "company": "********.**",
        "location": "*** ****, ****** ******",
        "date_posted": "Recent",
        "url": "https://www.linkedin.com/jobs/view/software-engineer-ii-active-hiring-at-jobright-ai-4242624027?position=7&pageNum=0&refId=u8ZB%2BbKAIaPKv3ULIz2CVA%3D%3D&trackingId=sb6N79%2B%2FN9z7DlQYeX5PqA%3D%3D",
        "source": "LinkedIn",
        "scraped_date": "2025-06-05 08:48:32",
        "email_sent": false
    },
    {
        "title": "Software Engineer (Junior & New Grad)",
        "company": "Jobright.ai",
        "location": "Washington, United States",
        "date_posted": "Recent",
        "url": "https://www.linkedin.com/jobs/view/software-engineer-junior-new-grad-at-jobright-ai-4242623346?position=2&pageNum=0&refId=CaKX8wP9OxtPbAZ0IDLeVw%3D%3D&trackingId=Sy5JCGKG%2FHckxna7OEKuNQ%3D%3D",
        "source": "LinkedIn",
        "scraped_date": "2025-06-05 09:00:49",
        "email_sent": false
    },
    {
        "title": "Software Engineer, ML Infra (Active Hiring)",
        "company": "Jobright.ai",
        "location": "California, United States",
        "date_posted": "Recent",
        "url": "https://www.linkedin.com/jobs/view/software-engineer-ml-infra-active-hiring-at-jobright-ai-4238025319?position=3&pageNum=0&refId=CaKX8wP9OxtPbAZ0IDLeVw%3D%3D&trackingId=XWBsZw86QnikFM%2BPT47WtA%3D%3D",
        "source": "LinkedIn",
        "scraped_date": "2025-06-05 09:00:49",
        "email_sent": false
    },
    {
        "title": "******** ********, ***",
        "company": "********.**",
        "location": "******** ****, **",
        "date_posted": "Recent",
        "url": "https://www.linkedin.com/jobs/view/software-engineer-web-at-jobright-ai-4242625013?position=5&pageNum=0&refId=CaKX8wP9OxtPbAZ0IDLeVw%3D%3D&trackingId=7BtnxPIsb57zK0cd1%2FGx5w%3D%3D",
        "source": "LinkedIn",
        "scraped_date": "2025-06-05 09:00:49",
        "email_sent": false
    },
    {
        "title": "Data Engineer",
        "company": "Glencore",
        "location": "New York, United States",
        "date_posted": "Recent",
        "url": "https://www.linkedin.com/jobs/view/data-engineer-at-glencore-4227655962?position=1&pageNum=0&refId=ScqXLYgd1uF3MtA6ufitFA%3D%3D&trackingId=Bf0rVJg%2B49Fk%2FTkJRPJ5Hw%3D%3D",
        "source": "LinkedIn",
        "scraped_date": "2025-06-05 09:29:28",
        "email_sent": true
    },
    {
        "title": "Engineer I - Data Links",
        "company": "JT4",
        "location": "Edwards, CA",
        "date_posted": "Recent",
        "url": "https://www.linkedin.com/jobs/view/engineer-i-data-links-at-jt4-4089009910?position=2&pageNum=0&refId=ScqXLYgd1uF3MtA6ufitFA%3D%3D&trackingId=WTbFlv4NDROJjRmerCfilA%3D%3D",
        "source": "LinkedIn",
        "scraped_date": "2025-06-05 09:29:28",
        "email_sent": false
    },
    {
        "title": "** ******** - ********",
        "company": "*** *****'* *******",
        "location": "****** ******",
        "date_posted": "Recent",
        "url": "https://www.linkedin.com/jobs/view/sr-engineer-software-at-the-wendy-s-company-4195249398?position=4&pageNum=0&refId=ScqXLYgd1uF3MtA6ufitFA%3D%3D&trackingId=S28lzhS64bdVxEgS32B9ug%3D%3D",
        "source": "LinkedIn",
        "scraped_date": "2025-06-05 09:29:28",
        "email_sent": false
    },
    {
        "title": "******** ******** (****** & *** ****)",
        "company": "********.**",
        "location": "**********, ****** ******",
        "date_posted": "Recent",
        "url": "https://www.linkedin.com/jobs/view/software-engineer-junior-new-grad-at-jobright-ai-4242623346?position=5&pageNum=0&refId=ScqXLYgd1uF3MtA6ufitFA%3D%3D&trackingId=HAIt7tC5KZUXr56UlAC9mA%3D%3D",
        "source": "LinkedIn",
        "scraped_date": "2025-06-05 09:29:28",
        "email_sent": false
    },
    {
        "title": "******** *********** ***** ********",
        "company": "********",
        "location": "***** ****, **",
        "date_posted": "Recent",
        "url": "https://www.linkedin.com/jobs/view/software-development-staff-engineer-at-experian-4215946336?position=6&pageNum=0&refId=ScqXLYgd1uF3MtA6ufitFA%3D%3D&trackingId=bT74cP1dc0CGrL6GQsidcQ%3D%3D",
        "source": "LinkedIn",
        "scraped_date": "2025-06-05 09:29:28",
        "email_sent": false
    },
    {
        "title": "Software Engineer - Database Engineering",
        "company": "Snowflake",
        "location": "Bellevue, WA",
        "date_posted": "Recent",
        "url": "https://www.linkedin.com/jobs/view/software-engineer-database-engineering-at-snowflake-4192198912?position=2&pageNum=0&refId=RVbM1A%2Bjn6pYbhZ%2Bq9ecPw%3D%3D&trackingId=2cXzeu74y59gpRLHnKW3Iw%3D%3D",
        "source": "LinkedIn",
        "scraped_date": "2025-06-05 09:45:47",
        "email_sent": true
    },
    {
        "title": "**** *******",
        "company": "*** ***********",
        "location": "****** ******",
        "date_posted": "Recent",
        "url": "https://www.linkedin.com/jobs/view/data-analyst-at-arb-interactive-4227524577?position=5&pageNum=0&refId=RVbM1A%2Bjn6pYbhZ%2Bq9ecPw%3D%3D&trackingId=%2FtgUVW1Je08axm4XqGV8JQ%3D%3D",
        "source": "LinkedIn",
        "scraped_date": "2025-06-05 09:45:47",
        "email_sent": false
    }
]