[
    {
        "title": "******** ******** (*** / **** *** **********)",
        "company": "***** ****",
        "location": "****** ******",
        "date_posted": "Recent",
        "url": "https://www.linkedin.com/jobs/view/software-engineer-opt-stem-opt-candidates-at-prana-path-4248685739?position=5&pageNum=0&refId=yk0HjgPZiiss8L3dkBlBHg%3D%3D&trackingId=a%2Bm35LlYEdpen2i1pHnvIA%3D%3D",
        "source": "LinkedIn",
        "scraped_date": "2025-06-11 07:56:24",
        "email_sent": false
    },
    {
        "title": "Data Analyst - Entry Level",
        "company": "TEKsystems",
        "location": "Oklahoma City, OK",
        "date_posted": "Recent",
        "url": "https://www.linkedin.com/jobs/view/data-analyst-entry-level-at-teksystems-4248692317?position=2&pageNum=0&refId=4ohwv2JDfQNgCjJ7RoAm2A%3D%3D&trackingId=V2iIQYcpgRePSdXF42Cs5Q%3D%3D",
        "source": "LinkedIn",
        "scraped_date": "2025-06-11 08:26:10",
        "email_sent": true
    },
    {
        "title": "Data Entry Analyst (Hybrid)",
        "company": "TEKsystems",
        "location": "Phoenix, AZ",
        "date_posted": "Recent",
        "url": "https://www.linkedin.com/jobs/view/data-entry-analyst-hybrid-at-teksystems-4248602488?position=3&pageNum=0&refId=4ohwv2JDfQNgCjJ7RoAm2A%3D%3D&trackingId=q0JV1Dys9Xw%2FJky7wY8Tiw%3D%3D",
        "source": "LinkedIn",
        "scraped_date": "2025-06-11 08:26:10",
        "email_sent": true
    },
    {
        "title": "******** ******** ** - ********* **********",
        "company": "********",
        "location": "*** *********, **",
        "date_posted": "Recent",
        "url": "https://www.linkedin.com/jobs/view/software-engineer-ii-developer-experience-at-rippling-4248691474?position=7&pageNum=0&refId=4ohwv2JDfQNgCjJ7RoAm2A%3D%3D&trackingId=GnzqqZE8MuJhvVg5EkoLkQ%3D%3D",
        "source": "LinkedIn",
        "scraped_date": "2025-06-11 08:26:10",
        "email_sent": false
    },
    {
        "title": "**** ***** **** ******** ********",
        "company": "**** ***** ******** ************* (*.*.) ***",
        "location": "**** *****, **",
        "date_posted": "Recent",
        "url": "https://www.linkedin.com/jobs/view/full-stack-data-software-engineer-at-booz-allen-hamilton-international-u-k-ltd-4248699266?position=7&pageNum=0&refId=aHk4i%2BVFOA%2Be2qPrl691qQ%3D%3D&trackingId=o5bN5LDPcQNMMFtFpMrAuw%3D%3D",
        "source": "LinkedIn",
        "scraped_date": "2025-06-11 08:49:26",
        "email_sent": false
    }
]