[
    {
        "title": "******** ********, **** ********",
        "company": "********",
        "location": "*** *********, **",
        "date_posted": "Recent",
        "url": "https://www.linkedin.com/jobs/view/software-engineer-data-mobility-at-doordash-4076037033?position=4&pageNum=0&refId=43WxIVYqLSFFQWOKe0elXA%3D%3D&trackingId=vB%2FKv02%2FevfYghpZTVzRLw%3D%3D",
        "source": "LinkedIn",
        "scraped_date": "2025-06-02 09:30:29",
        "email_sent": false
    },
    {
        "title": "*****-***** ******** ********",
        "company": "************ **",
        "location": "******** *******, **",
        "date_posted": "Recent",
        "url": "https://www.linkedin.com/jobs/view/entry-level-software-engineer-at-remoteworker-us-4242542100?position=5&pageNum=0&refId=43WxIVYqLSFFQWOKe0elXA%3D%3D&trackingId=bC1hNIaBOk%2FuIUufCH3urQ%3D%3D",
        "source": "LinkedIn",
        "scraped_date": "2025-06-02 09:30:29",
        "email_sent": false
    },
    {
        "title": "**********",
        "company": "**** *** ****** ******* *** *****",
        "location": "*** *****, **",
        "date_posted": "Recent",
        "url": "https://www.linkedin.com/jobs/view/technology-at-hire-our-heroes-veteran-job-board-4242552404?position=6&pageNum=0&refId=43WxIVYqLSFFQWOKe0elXA%3D%3D&trackingId=O4uMJO%2FJ3viSLLn8cAzXFw%3D%3D",
        "source": "LinkedIn",
        "scraped_date": "2025-06-02 09:30:29",
        "email_sent": false
    },
    {
        "title": "************ ******* (*****)",
        "company": "********* ******* **********",
        "location": "*** ****, ****** ******",
        "date_posted": "Recent",
        "url": "https://www.linkedin.com/jobs/view/quantitative-analyst-rates-at-bluecrest-capital-management-4152472506?position=7&pageNum=0&refId=43WxIVYqLSFFQWOKe0elXA%3D%3D&trackingId=S7r3PFgJmwLBa11O79aadQ%3D%3D",
        "source": "LinkedIn",
        "scraped_date": "2025-06-02 09:30:29",
        "email_sent": false
    },
    {
        "title": "Software Engineer, Data Mobility",
        "company": "DoorDash",
        "location": "San Francisco, CA",
        "date_posted": "Recent",
        "url": "https://www.linkedin.com/jobs/view/software-engineer-data-mobility-at-doordash-4076037033?position=1&pageNum=0&refId=v%2FCIQxwN3zvHRyartWP%2F1Q%3D%3D&trackingId=xGgGQ0HQ7yoVVjVf3g65Yw%3D%3D",
        "source": "LinkedIn",
        "scraped_date": "2025-06-02 10:20:36",
        "email_sent": true
    },
    {
        "title": "Entry-Level Software Engineer",
        "company": "RemoteWorker US",
        "location": "Maryland Heights, MO",
        "date_posted": "Recent",
        "url": "https://www.linkedin.com/jobs/view/entry-level-software-engineer-at-remoteworker-us-4242542100?position=2&pageNum=0&refId=v%2FCIQxwN3zvHRyartWP%2F1Q%3D%3D&trackingId=iyU%2FQNHxODkRAkauuRCfjg%3D%3D",
        "source": "LinkedIn",
        "scraped_date": "2025-06-02 10:20:36",
        "email_sent": false
    },
    {
        "title": "********* ******** ******** - ***++/***** ****",
        "company": "*********",
        "location": "*** ****, **",
        "date_posted": "Recent",
        "url": "https://www.linkedin.com/jobs/view/principal-software-engineer-sql%2B%2B-query-team-at-couchbase-4133472772?position=5&pageNum=0&refId=v%2FCIQxwN3zvHRyartWP%2F1Q%3D%3D&trackingId=rbeipSnHw43GX%2BmuyXoX1A%3D%3D",
        "source": "LinkedIn",
        "scraped_date": "2025-06-02 10:20:36",
        "email_sent": false
    },
    {
        "title": "********** (******) ******** (***** ******/**** ******)",
        "company": "*****",
        "location": "********, **",
        "date_posted": "Recent",
        "url": "https://www.linkedin.com/jobs/view/mechanical-fluids-engineer-fluid-system-pump-design-at-attis-4242558408?position=6&pageNum=0&refId=v%2FCIQxwN3zvHRyartWP%2F1Q%3D%3D&trackingId=%2BGaa%2FcGlweLaVDSdQhLYGA%3D%3D",
        "source": "LinkedIn",
        "scraped_date": "2025-06-02 10:20:36",
        "email_sent": false
    },
    {
        "title": "******** ********, ***** ******** - ******* ********",
        "company": "******* *******",
        "location": "*** *****, **",
        "date_posted": "Recent",
        "url": "https://www.linkedin.com/jobs/view/software-engineer-legal-prompter-spanish-speaking-at-thomson-reuters-4153481907?position=7&pageNum=0&refId=v%2FCIQxwN3zvHRyartWP%2F1Q%3D%3D&trackingId=CbjQ0%2FzXgsueBipv%2FnRKsw%3D%3D",
        "source": "LinkedIn",
        "scraped_date": "2025-06-02 10:20:36",
        "email_sent": false
    }
]